wingsys/__init__.py
wingsys/main/__init__.py
wingsys/main/all.py
wingsys/main/test.py
wingsys-0.4.dist-info/LICENSE
wingsys-0.4.dist-info/METADATA
wingsys-0.4.dist-info/WHEEL
wingsys-0.4.dist-info/top_level.txt
wingsys-0.4.dist-info/RECORD
