Metadata-Version: 2.1
Name: wingsys
Version: 0.4
Summary: Create console games
Home-page: https://www.github.com/mgismissing/gs
Author: magnesium
Author-email: hackergreg2000@gmail.com
Classifier: Development Status :: 5 - Production/Stable
Classifier: Programming Language :: Python :: 3
Classifier: License :: OSI Approved :: MIT License
License-File: LICENSE
Requires-Dist: colorama
Requires-Dist: keyboard
Requires-Dist: click
